<annotation>
	<folder></folder>
	<filename>TASS38012699_jpg.rf.19feb0c4e3d6743b6b558f19e8b2f910.jpg</filename>
	<path>TASS38012699_jpg.rf.19feb0c4e3d6743b6b558f19e8b2f910.jpg</path>
	<source>
		<database>roboflow.ai</database>
	</source>
	<size>
		<width>128</width>
		<height>128</height>
		<depth>3</depth>
	</size>
	<segmented>0</segmented>
	<object>
		<name>no-mask</name>
		<pose>Unspecified</pose>
		<truncated>0</truncated>
		<difficult>0</difficult>
		<occluded>0</occluded>
		<bndbox>
			<xmin>41</xmin>
			<xmax>48</xmax>
			<ymin>60</ymin>
			<ymax>71</ymax>
		</bndbox>
	</object>
	<object>
		<name>no-mask</name>
		<pose>Unspecified</pose>
		<truncated>0</truncated>
		<difficult>0</difficult>
		<occluded>0</occluded>
		<bndbox>
			<xmin>16</xmin>
			<xmax>27</xmax>
			<ymin>69</ymin>
			<ymax>87</ymax>
		</bndbox>
	</object>
	<object>
		<name>no-mask</name>
		<pose>Unspecified</pose>
		<truncated>0</truncated>
		<difficult>0</difficult>
		<occluded>0</occluded>
		<bndbox>
			<xmin>27</xmin>
			<xmax>41</xmax>
			<ymin>88</ymin>
			<ymax>114</ymax>
		</bndbox>
	</object>
	<object>
		<name>no-mask</name>
		<pose>Unspecified</pose>
		<truncated>0</truncated>
		<difficult>0</difficult>
		<occluded>0</occluded>
		<bndbox>
			<xmin>110</xmin>
			<xmax>119</xmax>
			<ymin>47</ymin>
			<ymax>68</ymax>
		</bndbox>
	</object>
	<object>
		<name>no-mask</name>
		<pose>Unspecified</pose>
		<truncated>0</truncated>
		<difficult>0</difficult>
		<occluded>0</occluded>
		<bndbox>
			<xmin>37</xmin>
			<xmax>53</xmax>
			<ymin>82</ymin>
			<ymax>108</ymax>
		</bndbox>
	</object>
	<object>
		<name>no-mask</name>
		<pose>Unspecified</pose>
		<truncated>0</truncated>
		<difficult>0</difficult>
		<occluded>0</occluded>
		<bndbox>
			<xmin>52</xmin>
			<xmax>61</xmax>
			<ymin>40</ymin>
			<ymax>56</ymax>
		</bndbox>
	</object>
	<object>
		<name>no-mask</name>
		<pose>Unspecified</pose>
		<truncated>0</truncated>
		<difficult>0</difficult>
		<occluded>0</occluded>
		<bndbox>
			<xmin>1</xmin>
			<xmax>4</xmax>
			<ymin>61</ymin>
			<ymax>84</ymax>
		</bndbox>
	</object>
	<object>
		<name>mask</name>
		<pose>Unspecified</pose>
		<truncated>0</truncated>
		<difficult>0</difficult>
		<occluded>0</occluded>
		<bndbox>
			<xmin>64</xmin>
			<xmax>77</xmax>
			<ymin>13</ymin>
			<ymax>40</ymax>
		</bndbox>
	</object>
</annotation>
